best4nicegui/__init__.py
best4nicegui/bi/__index.py
best4nicegui/bi/__init__.py
best4nicegui/bi/signature.py
best4nicegui/bi/source.py
best4nicegui/bi/echarts/ECharts.js
best4nicegui/bi/echarts/ECharts.py
best4nicegui/bi/echarts/__init__.py
best4nicegui/reactive/__index.py
best4nicegui/reactive/__init__.py
best4nicegui/reactive/official.py
best4nicegui/reactive/ref.py
best4nicegui/reactive/signature.py
best4nicegui/utils/__init__.py
best4nicegui/utils/signals.py
best4nicegui/utils/types.py
best4nicegui-0.1.0.data/data/echarts/ECharts.js
best4nicegui-0.1.0.dist-info/LICENSE
best4nicegui-0.1.0.dist-info/METADATA
best4nicegui-0.1.0.dist-info/WHEEL
best4nicegui-0.1.0.dist-info/top_level.txt
best4nicegui-0.1.0.dist-info/RECORD
